{
  "entries": [
    {
      "signature": "public override void Dispose ();",
      "docId": "M:SkiaSharp.Views.Gtk.SKDrawingArea.Dispose",
      "fields": {
        "summary": "Releases the resources used by the current instance of the <see cref=\"T:SkiaSharp.Views.Gtk.SKDrawingArea\" /> class.",
        "remarks": ""
      },
      "memberName": "Dispose",
      "memberType": "Method"
    }
  ],
  "typeName": "SkiaSharp.Views.Gtk.SKDrawingArea",
  "file": "/home/runner/work/SkiaSharp-API-docs/SkiaSharp-API-docs/SkiaSharpAPI/SkiaSharp.Views.Gtk/SKDrawingArea.xml"
}